hello.py
llmenvs-0.0.0.dist-info/METADATA
llmenvs-0.0.0.dist-info/WHEEL
llmenvs-0.0.0.dist-info/top_level.txt
llmenvs-0.0.0.dist-info/RECORD
