Metadata-Version: 2.2
Name: llmenvs
Version: 0.0.0
Summary: Coming soon
Author-email: William Brown <williambrown97@gmail.com>
